<?xml version="1.0" encoding="UTF-8"?>
<!DOCTYPE MBTINIT SYSTEM "../../templates/mbt_setup.dtd" >
<MBTINIT EXTENDED="true" EXECUTOR="none">
	<MODEL PATH="graphml/reqtags/ExtendedMain.graphml"/>
	<SCRIPT PATH="graphml/reqtags/graph.bsh"/>
	<SCRIPT PATH="graphml/reqtags/mbt_startup.bsh"/>
	<SCRIPT>
		v.add("Option 1");
		x = 0;
	</SCRIPT>
	<GENERATOR TYPE="RANDOM">
		<CONDITION TYPE="EDGE_COVERAGE" VALUE="10"/>
	</GENERATOR>
	<GENERATOR TYPE="RANDOM">
	 	<AND>
			<CONDITION TYPE="STATE_COVERAGE" VALUE="30"/>
			<CONDITION TYPE="EDGE_COVERAGE" VALUE="10"/>
		</AND>
	</GENERATOR>
</MBTINIT>
